mac_voice_assistant/AI.py
mac_voice_assistant/__init__.py
mac_voice_assistant/default_intents.json
mac_voice_assistant/IA/IA.py
mac_voice_assistant/IA/__init__.py
mac_voice_assistant/audio_samples/__init__.py
mac_voice_assistant/audio_samples/beep.wav
mac_voice_assistant/utils/__init__.py
mac_voice_assistant/utils/logger.py
tests/__init__.py
tests/example.py
tests/my_hotkey.py
tests/test.py
tests/text_typing.py
tests/voices.py
mac_voice_assistant-0.3.2.dist-info/LICENSE
mac_voice_assistant-0.3.2.dist-info/METADATA
mac_voice_assistant-0.3.2.dist-info/WHEEL
mac_voice_assistant-0.3.2.dist-info/top_level.txt
mac_voice_assistant-0.3.2.dist-info/RECORD
