Metadata-Version: 2.1
Name: mac-voice-assistant
Version: 0.3.2
Summary: A voice assistant prototype
Home-page: https://pypi.org/project/mac-voice-assistant/
Author: Manish Raj
Author-email: Manish Raj <manishraj1.618@gmail.com>
Project-URL: Homepage, https://github.com/Cre5cend0/mac
Project-URL: Bug Tracker, https://github.com/Cre5cend0/mac/issues
Keywords: python,mac,voice,assistant
Classifier: Development Status :: 1 - Planning
Classifier: Programming Language :: Python :: 3
Classifier: License :: OSI Approved :: MIT License
Classifier: Operating System :: MacOS :: MacOS X
Classifier: Environment :: Web Environment
Classifier: Intended Audience :: Developers
Classifier: Topic :: Software Development :: Build Tools
Classifier: Topic :: Software Development :: Libraries :: Python Modules
Requires-Python: >=3.7
License-File: LICENSE
Requires-Dist: numpy (>=1.24.0)
Requires-Dist: nltk (>=3.8)
Requires-Dist: tensorflow (>=2.11.0)
Requires-Dist: PyAudio (==0.2.12)
Requires-Dist: playsound (>=1.3.0)
Requires-Dist: pyttsx3 (>=2.90)
Requires-Dist: SpeechRecognition (==3.8.1)
Requires-Dist: pyjokes (>=0.6.0)
